lambo.py
lambo-0.4.0.dist-info/LICENSE
lambo-0.4.0.dist-info/WHEEL
lambo-0.4.0.dist-info/METADATA
lambo-0.4.0.dist-info/RECORD
