Metadata-Version: 2.1
Name: lambo
Version: 0.4.0
Summary: Simple and visually pleasing logger for AWS Lambda
Author-email: Alexander Mancevice <alexander.mancevice@hey.com>
Requires-Python: >= 3.7
Classifier: Development Status :: 5 - Production/Stable
Classifier: Environment :: Console
Classifier: Intended Audience :: Developers
Classifier: License :: OSI Approved :: MIT License
Classifier: Operating System :: OS Independent
Classifier: Programming Language :: Python :: 3
Classifier: Programming Language :: Python :: 3.7
Classifier: Programming Language :: Python :: 3.8
Classifier: Programming Language :: Python :: 3.9
Classifier: Programming Language :: Python :: 3.10
Classifier: Programming Language :: Python :: 3.11
Classifier: Programming Language :: Python :: 3.12
Classifier: Topic :: Utilities
Project-URL: Home, https://github.com/amancevice/python-lambo
